{"version":1,"resource":"file:///home/bicutoru/Documents/AtlasFinanceApp/app-atlas-finance/src/pages/register/document.tsx","entries":[{"id":"QR2d.tsx","timestamp":1723136566184},{"id":"QfL2.tsx","timestamp":1723146351889},{"id":"bLEZ.tsx","timestamp":1723146371426},{"id":"rdaf.tsx","timestamp":1723146443972},{"id":"wk9T.tsx","timestamp":1723146468429},{"id":"DBy7.tsx","timestamp":1723146504049},{"id":"hefW.tsx","timestamp":1723146520586},{"id":"H8H8.tsx","timestamp":1723146549252},{"id":"v4U8.tsx","timestamp":1723146560069}]}