{"version":1,"resource":"file:///home/bicutoru/Documents/AtlasFinanceApp/AtlasFx-AppBase/src/app/%28home%29/extract/comprovante/style.ts","entries":[{"id":"8QKV.ts","timestamp":1727730546415},{"id":"mpwz.ts","timestamp":1727730560672},{"id":"1fXs.ts","timestamp":1727795201746},{"id":"FnoV.ts","timestamp":1727795217296},{"id":"bGMV.ts","timestamp":1727795283716},{"id":"V9Ke.ts","timestamp":1727795295076},{"id":"Jtsx.ts","timestamp":1727795309806},{"id":"xwpK.ts","timestamp":1727795375052},{"id":"ffP9.ts","timestamp":1727795391996},{"id":"cC5k.ts","source":"Workspace Edit","timestamp":1727967647537},{"id":"PESV.ts","source":"Workspace Edit","timestamp":1727967770810},{"id":"h12q.ts","timestamp":1727968026807},{"id":"LlW2.ts","source":"undoRedo.source","timestamp":1727968035210},{"id":"uRXz.ts","timestamp":1728417639071},{"id":"Ej56.ts","timestamp":1728417665968},{"id":"H4Nf.ts","timestamp":1728419766503}]}