{"version":1,"resource":"file:///home/bicutoru/Documents/AtlasFinanceApp/AtlasFx-AppBase/src/components/DropdownWithText/index.tsx","entries":[{"id":"moU6.tsx","source":"Workspace Edit","timestamp":1727381358971},{"id":"NeJp.tsx","timestamp":1727381441741},{"id":"t1Jk.tsx","timestamp":1727381514744},{"id":"obdl.tsx","timestamp":1727381646047},{"id":"XbCh.tsx","timestamp":1727381666691},{"id":"BXNZ.tsx","timestamp":1727381704637},{"id":"3Q9d.tsx","timestamp":1727381734327},{"id":"TKFo.tsx","timestamp":1727381831827},{"id":"BQTH.tsx","timestamp":1727381846421},{"id":"1sJb.tsx","timestamp":1727382017241},{"id":"tKBF.tsx","timestamp":1727382051927},{"id":"1ppT.tsx","timestamp":1727382094867},{"id":"1n2B.tsx","timestamp":1727382362204},{"id":"rHYg.tsx","timestamp":1727382573981},{"id":"dANF.tsx","timestamp":1727382600111},{"id":"yHnn.tsx","timestamp":1727382678541},{"id":"sc3N.tsx","timestamp":1729711485497},{"id":"gcFP.tsx","timestamp":1729711506701}]}