{"version":1,"resource":"file:///home/bicutoru/Documents/AtlasFinanceApp/app-atlas-finance/src/assets/translate/i18n.tsx","entries":[{"id":"CZOg.ts","timestamp":1722952257088},{"id":"Arr2.ts","timestamp":1722952275693},{"id":"ppxu.ts","timestamp":1722952308956},{"id":"3PlB.ts","timestamp":1722952499325},{"id":"j7T9.ts","timestamp":1722959638085},{"id":"GHnN.ts","timestamp":1722959681651},{"id":"JqJ2.ts","timestamp":1722960437532},{"id":"OrtH.ts","timestamp":1722960725052},{"id":"qTUt.ts","timestamp":1722972062466},{"id":"cHUt.ts","timestamp":1722972083176},{"id":"HDAm.tsx","source":"renamed.source","sourceDescription":"~/Documents/AtlasFinanceApp/app-atlas-finance/src/assets/translate/i18n.ts","timestamp":1722973854916},{"id":"gvsu.tsx","timestamp":1722973868828},{"id":"Tiy5.tsx","timestamp":1722974263928},{"id":"mXvc.tsx","timestamp":1722974497495},{"id":"XYIU.tsx","timestamp":1722975037775},{"id":"PfGp.tsx","timestamp":1722975569865},{"id":"Y7eA.tsx","timestamp":1722975701165},{"id":"Ypms.tsx","timestamp":1722975722215},{"id":"F9f5.tsx","timestamp":1722975746355},{"id":"uGNk.tsx","timestamp":1722975773299},{"id":"GEp4.tsx","timestamp":1722975796222},{"id":"sQRc.tsx","timestamp":1722975808905},{"id":"aI3M.tsx","timestamp":1722975826832},{"id":"DlMe.tsx","timestamp":1722976047782},{"id":"pwSL.tsx","timestamp":1722976342372}]}